flask_sqlalchemy_db_orchestration/CHANGELOG.md
flask_sqlalchemy_db_orchestration/DbCreate.py
flask_sqlalchemy_db_orchestration/DbInit.py
flask_sqlalchemy_db_orchestration/DbMigrade.py
flask_sqlalchemy_db_orchestration/README.md
flask_sqlalchemy_db_orchestration/Requirements.txt
flask_sqlalchemy_db_orchestration/__init__.py
flask_sqlalchemy_db_orchestration/Logix/__init__.py
flask_sqlalchemy_db_orchestration/Logix/DbManager/DbManager.py
flask_sqlalchemy_db_orchestration/Logix/DbManager/__init__.py
flask_sqlalchemy_db_orchestration/Logix/Midware/CreateMigrationMaker.py
flask_sqlalchemy_db_orchestration/Logix/Midware/HeroKit.py
flask_sqlalchemy_db_orchestration/Logix/Midware/Multiple.py
flask_sqlalchemy_db_orchestration/Logix/Midware/RunMigration.py
flask_sqlalchemy_db_orchestration/Logix/Midware/Single.py
flask_sqlalchemy_db_orchestration/Logix/Temp/__init__.py
flask_sqlalchemy_db_orchestration/Logix/__pycache__/__init__.cpython-39.pyc
flask_sqlalchemy_db_orchestration/Models/__init__.py
flask_sqlalchemy_db_orchestration/Models/BaseModel/BaseModel.py
flask_sqlalchemy_db_orchestration/Models/BaseModel/__init__.py
flask_sqlalchemy_db_orchestration/Models/Entity/TestAuthentications.py
flask_sqlalchemy_db_orchestration/Models/Entity/TestUnits.py
flask_sqlalchemy_db_orchestration/Models/Entity/TestUsers.py
flask_sqlalchemy_db_orchestration/Models/Entity/_EntityExport.py
flask_sqlalchemy_db_orchestration/Models/Entity/__init__.py
flask_sqlalchemy_db_orchestration/Models/__pycache__/__init__.cpython-39.pyc
flask_sqlalchemy_db_orchestration/Utils/GeneralConfig.json
flask_sqlalchemy_db_orchestration/Utils/SQLiteConfig.json
flask_sqlalchemy_db_orchestration-1.0.0.dist-info/LICENSE
flask_sqlalchemy_db_orchestration-1.0.0.dist-info/METADATA
flask_sqlalchemy_db_orchestration-1.0.0.dist-info/WHEEL
flask_sqlalchemy_db_orchestration-1.0.0.dist-info/top_level.txt
flask_sqlalchemy_db_orchestration-1.0.0.dist-info/RECORD
