Metadata-Version: 2.1
Name: flask-sqlalchemy-db-orchestration
Version: 1.0.0
Summary: A powerful tool for managing multiple database environments in Flask applications
Home-page: https://github.com/MuratBilginerSoft/Flask-SQLAlchemy-Database-Orchestration
Author: Murat Bilginer
Author-email: mbilginer@brainytech.net
License: UNKNOWN
Platform: UNKNOWN
Classifier: Programming Language :: Python :: 3
Classifier: License :: OSI Approved :: MIT License
Classifier: Operating System :: OS Independent
Requires-Python: >=3.6
License-File: LICENSE
Requires-Dist: alembic==1.15.1
Requires-Dist: blinker==1.9.0
Requires-Dist: click==8.1.8
Requires-Dist: colorama==0.4.6
Requires-Dist: Flask==3.1.0
Requires-Dist: Flask-Migrate==4.1.0
Requires-Dist: Flask-SQLAlchemy==3.1.1
Requires-Dist: greenlet==3.1.1
Requires-Dist: importlib-metadata==8.6.1
Requires-Dist: itsdangerous==2.2.0
Requires-Dist: Jinja2==3.1.6
Requires-Dist: Mako==1.3.9
Requires-Dist: MarkupSafe==3.0.2
Requires-Dist: psycopg2==2.9.10
Requires-Dist: PyMySQL==1.1.1
Requires-Dist: pyodbc==5.2.0
Requires-Dist: SQLAlchemy==2.0.39
Requires-Dist: typing-extensions==4.12.2
Requires-Dist: Werkzeug==3.1.3
Requires-Dist: zipp==3.21.0
